calculator/__init__.py
calculator/hegzbe2.py
calculator/mashinhesab.py
calculatoramirsadeg-0.1.dist-info/METADATA
calculatoramirsadeg-0.1.dist-info/WHEEL
calculatoramirsadeg-0.1.dist-info/top_level.txt
calculatoramirsadeg-0.1.dist-info/RECORD
