Metadata-Version: 2.1
Name: calculatoramirsadeg
Version: 0.1
Summary: this package for oct and math 
Author: amir hossein sadeghi nahr !
